XSocket/__init__.py
XSocket/client.py
XSocket/events.py
XSocket/exception.py
XSocket/server.py
XSocket/util.py
XSocket/core/__init__.py
XSocket/core/handle.py
XSocket/core/listener.py
XSocket/core/net.py
XSocket/core/socket.py
XSocket/protocol/__init__.py
XSocket/protocol/protocol.py
XSocket/protocol/inet/__init__.py
XSocket/protocol/inet/net.py
XSocket/protocol/inet/xtcp/__init__.py
XSocket/protocol/inet/xtcp/handle.py
XSocket/protocol/inet/xtcp/listener.py
XSocket/protocol/inet/xtcp/socket.py
XSocket-0.0.1a3.dist-info/LICENSE
XSocket-0.0.1a3.dist-info/METADATA
XSocket-0.0.1a3.dist-info/WHEEL
XSocket-0.0.1a3.dist-info/top_level.txt
XSocket-0.0.1a3.dist-info/RECORD
